README.txt
setup.py
newpacktest/__init__.py
newpacktest/third.py
newpacktest.egg-info/PKG-INFO
newpacktest.egg-info/SOURCES.txt
newpacktest.egg-info/dependency_links.txt
newpacktest.egg-info/top_level.txt
newpacktest.egg-info/zip-safe